setup.py
modulecatalog/__init__.py
modulecatalog/modulecatalog.py
pyang_module_catalog_plugin.egg-info/PKG-INFO
pyang_module_catalog_plugin.egg-info/SOURCES.txt
pyang_module_catalog_plugin.egg-info/dependency_links.txt
pyang_module_catalog_plugin.egg-info/entry_points.txt
pyang_module_catalog_plugin.egg-info/requires.txt
pyang_module_catalog_plugin.egg-info/top_level.txt