Metadata-Version: 1.0
Name: pyang-module-catalog-plugin
Version: 0.2
Summary: A pyang plugin to extract OpenConfig module catalog data from YANG modules
Home-page: https://github.com/cmoberg/pyang-module-catalog-plugin
Author: Carl Moberg
Author-email: camoberg@cisco.com
License: New-style BSD
Keywords: yang,extraction
Platform: UNKNOWN
